milvus_model/__init__.py
milvus_model/base.py
milvus_model/dense/__init__.py
milvus_model/dense/cohere.py
milvus_model/dense/instructor.py
milvus_model/dense/jinaai.py
milvus_model/dense/mistralai.py
milvus_model/dense/nomic.py
milvus_model/dense/onnx.py
milvus_model/dense/openai.py
milvus_model/dense/sentence_transformer.py
milvus_model/dense/voyageai.py
milvus_model/dense/instructor_embedding/instructor_impl.py
milvus_model/hybrid/__init__.py
milvus_model/hybrid/bge_m3.py
milvus_model/hybrid/mgte.py
milvus_model/reranker/__init__.py
milvus_model/reranker/bgereranker.py
milvus_model/reranker/cohere.py
milvus_model/reranker/cross_encoder.py
milvus_model/reranker/jinaai.py
milvus_model/reranker/voyageai.py
milvus_model/sparse/__init__.py
milvus_model/sparse/splade.py
milvus_model/sparse/utils.py
milvus_model/sparse/bm25/__init__.py
milvus_model/sparse/bm25/bm25.py
milvus_model/sparse/bm25/lang.yaml
milvus_model/sparse/bm25/tokenizers.py
milvus_model/utils/__init__.py
milvus_model/utils/dependency_control.py
milvus_model/utils/lazy_import.py
milvus_model-0.2.12.dist-info/LICENSE
milvus_model-0.2.12.dist-info/METADATA
milvus_model-0.2.12.dist-info/WHEEL
milvus_model-0.2.12.dist-info/top_level.txt
milvus_model-0.2.12.dist-info/RECORD
