Metadata-Version: 2.2
Name: milvus-model
Version: 0.2.12
Summary: Model components for PyMilvus, the Python SDK for Milvus
Author-email: Milvus Team <milvus-team@zilliz.com>
Project-URL: repository, https://github.com/milvus-io/milvus-model
Classifier: Programming Language :: Python :: 3
Classifier: License :: OSI Approved :: Apache Software License
Requires-Python: >=3.8
License-File: LICENSE
Requires-Dist: transformers>=4.36.0
Requires-Dist: onnxruntime
Requires-Dist: scipy>=1.10.0
Requires-Dist: protobuf
Requires-Dist: numpy
